Metadata-Version: 2.1
Name: django-cognito-jwt
Version: 0.0.4
Summary: Django backends for AWS Cognito JWT
Home-page: https://github.com/LabD/django-cognito-jwt
Author: Michael van Tellingen
Author-email: m.vantellingen@labdigital.nl
License: MIT
Platform: UNKNOWN
Classifier: Development Status :: 5 - Production/Stable
Classifier: Environment :: Web Environment
Classifier: Framework :: Django
Classifier: Framework :: Django :: 1.11
Classifier: License :: OSI Approved :: MIT License
Classifier: Programming Language :: Python
Classifier: Programming Language :: Python :: 3
Classifier: Programming Language :: Python :: 3.6
Classifier: Programming Language :: Python :: 3.7
Classifier: Programming Language :: Python :: 3.8
Provides-Extra: test
Provides-Extra: docs
